scvr/__init__.py
scvr/command_line.py
scvr/converters.py
scvr/palettes.py
scvr-1.1.dist-info/LICENSE
scvr-1.1.dist-info/METADATA
scvr-1.1.dist-info/WHEEL
scvr-1.1.dist-info/entry_points.txt
scvr-1.1.dist-info/top_level.txt
scvr-1.1.dist-info/RECORD
