Metadata-Version: 2.1
Name: scvr
Version: 1.1
Summary: single cell VR preprocess
Home-page: https://github.com/pinellolab/singlecellvr
Author: Huidong Chen
Author-email: huidong.chen@mgh.harvard.edu
License: UNKNOWN
Platform: UNKNOWN
Classifier: Programming Language :: Python :: 3
Classifier: License :: OSI Approved :: MIT License
Classifier: Operating System :: OS Independent
Requires-Python: >=3.6
Requires-Dist: pandas (>=0.21)
Requires-Dist: numpy (>=1.14.0)
Requires-Dist: networkx (>=2.1)
Requires-Dist: anndata (>=0.7)
Requires-Dist: loompy (>=2.0)
Requires-Dist: matplotlib (>=3.0)
Requires-Dist: scipy (>=1.3)
